demovae/__init__.py
demovae/model.py
demovae/sklearn.py
demovae-0.0.6.dist-info/METADATA
demovae-0.0.6.dist-info/WHEEL
demovae-0.0.6.dist-info/licenses/LICENSE
demovae-0.0.6.dist-info/RECORD
